{
    "name": "PL_laborforce_generation_industry_employ_codes",
    "properties": {
        "activities": [
            {
                "name": "CreateMetadataCodes",
                "type": "Script",
                "dependsOn": [],
                "policy": {
                    "timeout": "0.12:00:00",
                    "retry": 0,
                    "retryIntervalInSeconds": 30,
                    "secureOutput": false,
                    "secureInput": false
                },
                "userProperties": [],
                "linkedServiceName": {
                    "referenceName": "Connect_population_dynamics_prefecture",
                    "type": "LinkedServiceReference"
                },
                "typeProperties": {
                    "scripts": [
                        {
                            "type": "Query",
                            "text": "IF EXISTS (\n    SELECT 1\n    FROM sys.tables\n    WHERE name = 'laborforce_generation_industry_employ_code'\n)\nBEGIN\n    DROP TABLE laborforce_generation_industry_employ_code\nEND;\n\nCREATE TABLE laborforce_generation_industry_employ_code (\n    job_code INT NOT NULL PRIMARY KEY,\n    job_name NVARCHAR(200) NOT NULL,   \n);"
                        }
                    ],
                    "scriptBlockExecutionTimeout": "02:00:00"
                }
            },
            {
                "name": "CleanJobName",
                "description": "",
                "type": "Script",
                "dependsOn": [
                    {
                        "activity": "RawToMetadataCodes",
                        "dependencyConditions": [
                            "Completed"
                        ]
                    }
                ],
                "policy": {
                    "timeout": "0.12:00:00",
                    "retry": 0,
                    "retryIntervalInSeconds": 30,
                    "secureOutput": false,
                    "secureInput": false
                },
                "userProperties": [],
                "linkedServiceName": {
                    "referenceName": "Connect_population_dynamics_prefecture",
                    "type": "LinkedServiceReference"
                },
                "typeProperties": {
                    "scripts": [
                        {
                            "type": "Query",
                            "text": "-- job_name内の空白削除\nUPDATE laborforce_generation_industry_employ_code\nSET job_name = TRIM(BOTH ' ' FROM TRIM(BOTH '　' FROM job_name))"
                        }
                    ],
                    "scriptBlockExecutionTimeout": "02:00:00"
                }
            },
            {
                "name": "RawToMetadataCodes",
                "type": "Copy",
                "dependsOn": [
                    {
                        "activity": "CreateMetadataCodes",
                        "dependencyConditions": [
                            "Completed"
                        ]
                    }
                ],
                "policy": {
                    "timeout": "0.12:00:00",
                    "retry": 0,
                    "retryIntervalInSeconds": 30,
                    "secureOutput": false,
                    "secureInput": false
                },
                "userProperties": [],
                "typeProperties": {
                    "source": {
                        "type": "DelimitedTextSource",
                        "storeSettings": {
                            "type": "AzureBlobFSReadSettings",
                            "recursive": true,
                            "enablePartitionDiscovery": false
                        },
                        "formatSettings": {
                            "type": "DelimitedTextReadSettings"
                        }
                    },
                    "sink": {
                        "type": "DelimitedTextSink",
                        "storeSettings": {
                            "type": "AzureBlobFSWriteSettings"
                        },
                        "formatSettings": {
                            "type": "DelimitedTextWriteSettings",
                            "quoteAllText": true,
                            "fileExtension": ".txt"
                        }
                    },
                    "enableStaging": false,
                    "translator": {
                        "type": "TabularTranslator",
                        "mappings": [
                            {
                                "source": {
                                    "type": "String",
                                    "ordinal": 1
                                },
                                "sink": {
                                    "type": "String",
                                    "physicalType": "String",
                                    "ordinal": 1
                                }
                            },
                            {
                                "source": {
                                    "type": "String",
                                    "ordinal": 2
                                },
                                "sink": {
                                    "type": "String",
                                    "physicalType": "String",
                                    "ordinal": 2
                                }
                            }
                        ],
                        "typeConversion": true,
                        "typeConversionSettings": {
                            "allowDataTruncation": true,
                            "treatBooleanAsNumber": false
                        }
                    }
                },
                "inputs": [
                    {
                        "referenceName": "encode_raw_laborforce_generation_industry_employ_code",
                        "type": "DatasetReference"
                    }
                ],
                "outputs": [
                    {
                        "referenceName": "encode_raw_laborforce_generation_industry_employ_code",
                        "type": "DatasetReference"
                    }
                ]
            }
        ],
        "annotations": [],
        "lastPublishTime": "2026-03-30T00:54:44Z"
    },
    "type": "Microsoft.DataFactory/factories/pipelines"
}